exchange_calendars_extensions/core/__init__.py
exchange_calendars_extensions/core/holiday.py
exchange_calendars_extensions/core/holiday_calendar.py
exchange_calendars_extensions/core/offset.py
exchange_calendars_extensions/core/util.py
exchange_calendars_extensions-0.8.3.dist-info/METADATA
exchange_calendars_extensions-0.8.3.dist-info/WHEEL
exchange_calendars_extensions-0.8.3.dist-info/licenses/LICENSE
exchange_calendars_extensions-0.8.3.dist-info/RECORD
