Metadata-Version: 2.3
Name: exchange-calendars-extensions
Version: 0.8.3
Summary: Extensions of the exchange-calendars package
Author-email: Jens Keiner <jens.keiner@gmail.com>
License: Apache-2.0
Keywords: calendar,exchange,holidays,trading
Classifier: Development Status :: 4 - Beta
Classifier: Intended Audience :: Developers
Classifier: Intended Audience :: Financial and Insurance Industry
Classifier: Intended Audience :: Information Technology
Classifier: License :: OSI Approved :: Apache Software License
Classifier: Operating System :: OS Independent
Classifier: Programming Language :: Python
Classifier: Programming Language :: Python :: 3
Classifier: Programming Language :: Python :: 3.10
Classifier: Programming Language :: Python :: 3.11
Classifier: Programming Language :: Python :: 3.12
Classifier: Programming Language :: Python :: 3.13
Classifier: Topic :: Scientific/Engineering
Classifier: Topic :: Software Development :: Libraries :: Python Modules
Requires-Python: >=3.10
Requires-Dist: exchange-calendars-extensions-api<1,>=0.4.2
Requires-Dist: exchange-calendars<5,>=4.0.1
Requires-Dist: pydantic<3,>=2.0
Requires-Dist: typing-extensions<5,>=4.0
